[
  {
    "name": "中山桥",
    "city": "兰州",
    "category": "attraction",
    "description": "中山桥，位于甘肃省兰州市城关区，是兰州历史悠久的铁桥，被誉为\"天下黄河第一桥\"，是兰州市的标志性建筑之一。",
    "tags": [
      "风景名胜"
    ],
    "avgCost": 0,
    "duration": "1小时",
    "openTime": "全天",
    "rating": 4.5
  },
  {
    "name": "水车博览园",
    "city": "兰州",
    "category": "attraction",
    "description": "水车博览园是兰州的一个著名景点，展示了黄河水车文化。",
    "tags": [
      "风景名胜",
      "国家级景点"
    ],
    "avgCost": 0,
    "duration": "1-2小时",
    "openTime": "09:00-18:00",
    "rating": 4.5
  },
  {
    "name": "白塔山公园",
    "city": "兰州",
    "category": "attraction",
    "description": "白塔山公园位于兰州市城关区，北滨河中路，是兰州著名的风景名胜区和公园广场。公园以白塔寺为核心，登顶可俯瞰黄河和兰州全景，是游客和市民休闲观光的理想之地。",
    "tags": [
      "风景名胜",
      "公园",
      "广场"
    ],
    "avgCost": 0,
    "duration": "2小时",
    "openTime": "08:00-18:00",
    "rating": 4.5
  },
  {
    "name": "五泉山公园",
    "city": "兰州",
    "category": "attraction",
    "description": "五泉山公园位于甘肃省兰州市城关区，因有甘露、掬月、摸子、惠、蒙五眼泉水而得名，是一处著名的风景名胜区。",
    "tags": [
      "风景名胜",
      "公园",
      "兰州"
    ],
    "avgCost": 0,
    "duration": "2-3小时",
    "openTime": "06:00-22:00",
    "rating": 4.5
  },
  {
    "name": "兰州水车园",
    "city": "兰州",
    "category": "attraction",
    "description": "兰州水车园位于甘肃省兰州市七里河区，是一处展示黄河流域传统水车文化的主题公园。园内展示有大小不一的水车，再现了古代黄河沿岸的农耕灌溉场景，是了解兰州水车历史和文化的好去处。",
    "tags": [
      "风景名胜",
      "国家级景点"
    ],
    "avgCost": 0,
    "duration": "1-2小时",
    "openTime": "08:00-18:00",
    "rating": 4.2
  },
  {
    "name": "读者博物馆",
    "city": "兰州",
    "category": "attraction",
    "description": "读者博物馆位于兰州市城关区读者出版集团有限公司内，展示了《读者》杂志的创刊历史、发展历程及文化影响，是了解中国期刊文化的重要场所。",
    "tags": [
      "博物馆",
      "读者",
      "文化",
      "期刊"
    ],
    "avgCost": 0,
    "duration": "1-2小时",
    "openTime": "09:00-17:00",
    "rating": 4.5
  },
  {
    "name": "小西湖",
    "city": "兰州",
    "category": "attraction",
    "description": "小西湖位于兰州市七里河区西津东路，是一处集风景名胜、公园广场与休闲公园于一体的城市绿地。园内湖光潋滟，绿树成荫，是市民休闲娱乐的好去处，也是兰州著名的旅游景点之一。",
    "tags": [
      "风景名胜",
      "公园广场",
      "公园"
    ],
    "avgCost": 0,
    "duration": "2小时",
    "openTime": "全天开放",
    "rating": 4.0
  },
  {
    "name": "兰州市博物馆",
    "city": "兰州",
    "category": "attraction",
    "description": "兰州市博物馆 是兰州的旅游景点，位于城关区。地址：庆阳路240号(东方红广场地铁站X1口步行410米)。",
    "tags": [
      "兰州"
    ],
    "avgCost": 0,
    "duration": "",
    "openTime": "全天",
    "rating": 3.5
  },
  {
    "name": "五一山省级森林生态旅游区",
    "city": "兰州",
    "category": "attraction",
    "description": "五一山省级森林生态旅游区位于兰州市城关区，是一处集风景名胜与省级景点于一体的旅游区。",
    "tags": [
      "风景名胜",
      "省级景点"
    ],
    "avgCost": 0,
    "duration": "",
    "openTime": "",
    "rating": 0.0
  },
  {
    "name": "黄河第一桥石碑",
    "city": "兰州",
    "category": "attraction",
    "description": "黄河第一桥石碑是兰州市城关区的一处风景名胜，位于南滨河路与中山路交叉口附近，与黄河铁桥相伴，是兰州标志性景点之一。",
    "tags": [
      "风景名胜",
      "旅游景点"
    ],
    "avgCost": 0,
    "duration": "未知",
    "openTime": "全天",
    "rating": 0
  },
  {
    "name": "(清真)德元纯汤牛肉面-兰州总店",
    "city": "兰州",
    "category": "food",
    "description": "位于城关区嘉峪关西路的清真牛肉面馆，提供正宗兰州牛肉面。",
    "tags": [
      "清真",
      "牛肉面",
      "兰州美食"
    ],
    "avgCost": 20,
    "duration": "1小时",
    "openTime": "06:00-21:00",
    "rating": 4.5
  },
  {
    "name": "马安军辣子牛肉面(汇美商城店)",
    "city": "兰州",
    "category": "food",
    "description": "马安军辣子牛肉面位于兰州市七里河区敦煌路410号，是一家以辣子牛肉面为特色的清真中餐厅。",
    "tags": [
      "清真菜",
      "中餐",
      "牛肉面"
    ],
    "avgCost": 25,
    "duration": "1小时",
    "openTime": "06:30-14:00",
    "rating": 4.5
  },
  {
    "name": "吾穆勒蓬灰牛肉面",
    "city": "兰州",
    "category": "food",
    "description": "吾穆勒蓬灰牛肉面是兰州一家知名的清真牛肉面馆，位于北滨河中路，以使用蓬灰制作的面条著称，口感筋道，汤味醇厚。",
    "tags": [
      "牛肉面",
      "清真",
      "兰州"
    ],
    "avgCost": 20,
    "duration": "0.5小时",
    "openTime": "06:00-14:00",
    "rating": 4.5
  },
  {
    "name": "磨沟沿老字号牛肉面·清真(金港城店)",
    "city": "兰州",
    "category": "food",
    "description": "磨沟沿老字号牛肉面·清真(金港城店) 是兰州的美食餐厅，位于七里河区。地址：郑家庄14号华名烟酒。",
    "tags": [
      "兰州"
    ],
    "avgCost": 0,
    "duration": "",
    "openTime": "全天",
    "rating": 3.5
  },
  {
    "name": "再回首(木塔巷店)",
    "city": "兰州",
    "category": "food",
    "description": "再回首是兰州知名的连锁小吃店，木塔巷店位于西关商圈，以酿皮、甜醅、灰豆子等地道兰州小吃闻名，口味正宗，价格实惠，是体验当地美食的热门去处。",
    "tags": [
      "小吃",
      "兰州美食",
      "酿皮",
      "甜醅"
    ],
    "avgCost": 25,
    "duration": "30分钟",
    "openTime": "10:00-20:30",
    "rating": 4.3
  },
  {
    "name": "清真·祁师手抓(小西湖总店)",
    "city": "兰州",
    "category": "food",
    "description": "兰州老字号清真餐厅，以手抓羊肉闻名，肉质鲜嫩不膻，搭配秘制蘸料，是本地人和游客打卡的热门美食地。",
    "tags": [
      "清真",
      "手抓羊肉",
      "兰州美食",
      "西北菜",
      "小西湖"
    ],
    "avgCost": 80,
    "duration": "1-2小时",
    "openTime": "10:00-22:00",
    "rating": 4.5
  },
  {
    "name": "磨沟沿老字号牛肉面(农民巷店)",
    "city": "兰州",
    "category": "food",
    "description": "磨沟沿老字号牛肉面是兰州知名的牛肉面馆，以其醇厚的汤底和劲道的面条深受食客喜爱。位于城关区农民巷，西北宾馆家属院西南门旁，是本地人和游客打卡的经典店铺。",
    "tags": [
      "牛肉面",
      "兰州",
      "老字号"
    ],
    "avgCost": 25,
    "duration": "0.5小时",
    "openTime": "06:00-14:00",
    "rating": 4.5
  },
  {
    "name": "伊穆祥牛肉面总店(清真)",
    "city": "兰州",
    "category": "food",
    "description": "伊穆祥牛肉面总店(清真)位于皋兰县彩虹城A区东门南110米，是一家以清真牛肉面为特色的餐厅。店内面条劲道，汤底醇厚，牛肉鲜嫩，深受食客喜爱。",
    "tags": [
      "清真菜馆",
      "中餐厅",
      "牛肉面"
    ],
    "avgCost": 30,
    "duration": "1小时",
    "openTime": "06:00-22:00",
    "rating": 4.5
  },
  {
    "name": "清真·磨沟沿老字号牛肉面(安宁店)",
    "city": "兰州",
    "category": "food",
    "description": "清真·磨沟沿老字号牛肉面(安宁店)是一家位于兰州市安宁区的知名牛肉面馆，以传统工艺和地道风味著称，提供正宗的兰州牛肉面。",
    "tags": [
      "牛肉面",
      "清真",
      "兰州美食"
    ],
    "avgCost": 25,
    "duration": "1小时",
    "openTime": "06:00-14:00",
    "rating": 4.5
  },
  {
    "name": "清真·文果手抓(柏树巷店)",
    "city": "兰州",
    "category": "food",
    "description": "清真·文果手抓(柏树巷店)位于兰州市七里河区柏树巷，是一家以传统手抓羊肉为特色的清真餐馆。店内选用优质羊肉，烹制手法地道，肉质鲜嫩多汁，深受食客喜爱。餐厅环境整洁，服务热情，是体验兰州清真美食的好去处。",
    "tags": [
      "清真",
      "手抓羊肉",
      "兰州美食",
      "中餐厅"
    ],
    "avgCost": 80,
    "duration": "1-2小时",
    "openTime": "11:00-21:00",
    "rating": 4.5
  },
  {
    "name": "兰州云海宾馆(欣大购物广场店)",
    "city": "兰州",
    "category": "hotel",
    "description": "兰州云海宾馆位于兰州市城关区雁西路799号，靠近欣大购物广场，提供宾馆住宿服务。",
    "tags": [
      "住宿",
      "宾馆",
      "城关区"
    ],
    "avgCost": 0,
    "duration": "",
    "openTime": "",
    "rating": 3.5
  },
  {
    "name": "陇源宾馆",
    "city": "兰州",
    "category": "hotel",
    "description": "陇源宾馆位于雁北路3124号，提供舒适便捷的住宿服务，靠近新港城B区。",
    "tags": [
      "住宿",
      "宾馆",
      "城关区"
    ],
    "avgCost": 200,
    "duration": "1天",
    "openTime": "全天",
    "rating": 4.0
  },
  {
    "name": "兰州喜洋洋宾馆",
    "city": "兰州",
    "category": "hotel",
    "description": "位于兰州市城关区雁北路的宾馆，提供住宿服务。",
    "tags": [
      "住宿",
      "宾馆",
      "城关区"
    ],
    "avgCost": 0,
    "duration": "",
    "openTime": "",
    "rating": 3.5
  },
  {
    "name": "兰州青年旅馆",
    "city": "兰州",
    "category": "hotel",
    "description": "兰州青年旅馆 是兰州的景点",
    "tags": [],
    "avgCost": 0,
    "duration": "",
    "openTime": "",
    "rating": 0
  },
  {
    "name": "兰州银花宾馆",
    "city": "兰州",
    "category": "hotel",
    "description": "兰州银花宾馆位于城关区张苏滩416号，提供住宿服务。",
    "tags": [
      "住宿",
      "酒店"
    ],
    "avgCost": 150,
    "duration": "1晚",
    "openTime": "24小时",
    "rating": 4.0
  }
]