[
  {
    "name": "观山湖公园",
    "city": "贵阳",
    "category": "attraction",
    "description": "观山湖公园是位于贵阳市观山湖区的一个大型城市公园，以观山湖为核心，环境优美，适合休闲散步。",
    "tags": [
      "公园",
      "风景名胜",
      "休闲"
    ],
    "avgCost": 0,
    "duration": "2-3小时",
    "openTime": "全天开放",
    "rating": 4.5
  },
  {
    "name": "贵州省博物馆",
    "city": "贵阳",
    "category": "attraction",
    "description": "贵州省博物馆位于贵阳市观山湖区林城东路107号，是展示贵州历史文化和民族风情的重要场所。馆内收藏丰富，包括古生物化石、民族服饰、书画等珍贵文物。",
    "tags": [
      "博物馆",
      "贵州文化"
    ],
    "avgCost": 0,
    "duration": "2-3小时",
    "openTime": "09:00-17:00（周一闭馆）",
    "rating": 4.5
  },
  {
    "name": "泉湖公园",
    "city": "贵阳",
    "category": "attraction",
    "description": "泉湖公园位于贵阳市白云区云峰大道142号，是一处国家级风景名胜区，以优美的泉湖景观和自然风光著称，是休闲游览的好去处。",
    "tags": [
      "风景名胜",
      "国家级景点"
    ],
    "avgCost": 0,
    "duration": "",
    "openTime": "",
    "rating": 3.5
  },
  {
    "name": "混沌广场",
    "city": "贵阳",
    "category": "attraction",
    "description": "混沌广场位于贵阳市观山湖区金阳北路与南苑路交叉口西侧，是一个集商务办公、商业配套于一体的综合写字楼群。周边交通便利，配套设施完善，适合企业办公和商务活动。",
    "tags": [
      "商务住宅",
      "楼宇",
      "商务写字楼"
    ],
    "avgCost": 0,
    "duration": "暂无",
    "openTime": "",
    "rating": 0
  },
  {
    "name": "西普陀寺",
    "city": "贵阳",
    "category": "attraction",
    "description": "西普陀寺位于贵阳市白云区，是一座历史悠久的佛教寺庙，依山而建，环境清幽。寺内建筑古朴典雅，供奉多尊佛像，香火旺盛。游客可在此感受宁静的宗教氛围，俯瞰城市景色。",
    "tags": [
      "寺庙",
      "佛教",
      "风景名胜"
    ],
    "avgCost": 0,
    "duration": "1-2小时",
    "openTime": "08:00-17:00",
    "rating": 4.5
  },
  {
    "name": "贵州省地质博物馆",
    "city": "贵阳",
    "category": "attraction",
    "description": "贵州省地质博物馆是展示地质矿产和古生物化石的专业博物馆。",
    "tags": [
      "博物馆",
      "地质",
      "科教"
    ],
    "avgCost": 0,
    "duration": "2-3小时",
    "openTime": "09:00-17:00（周一闭馆）",
    "rating": 4.5
  },
  {
    "name": "贵阳欢乐世界",
    "city": "贵阳",
    "category": "attraction",
    "description": "贵阳欢乐世界位于白云区，是一个集游乐、休闲、体育于一体的大型主题乐园，拥有多种游乐设施，适合家庭游玩。",
    "tags": [
      "体育休闲",
      "休闲场所",
      "游乐场"
    ],
    "avgCost": 80,
    "duration": "3小时",
    "openTime": "09:00-18:00",
    "rating": 4.2
  },
  {
    "name": "贵阳市观山湖公园民族大联欢广场",
    "city": "贵阳",
    "category": "attraction",
    "description": "贵阳市观山湖公园内的民族大联欢广场是一个集文化展示、休闲娱乐于一体的城市广场，经常举办各类民族节庆活动，是游客感受贵州民族文化的好去处。",
    "tags": [
      "风景名胜",
      "公园广场",
      "城市广场"
    ],
    "avgCost": 0,
    "duration": "1-2小时",
    "openTime": "全天开放",
    "rating": 4.5
  },
  {
    "name": "贵阳喀斯特公园",
    "city": "贵阳",
    "category": "attraction",
    "description": "贵阳喀斯特公园位于观山湖区石林东路与金阳南路交叉口，是一个以喀斯特地貌为特色的城市公园。园内拥有独特的石林景观和丰富的植被，是市民休闲娱乐的好去处。",
    "tags": [
      "喀斯特",
      "公园",
      "风景",
      "休闲"
    ],
    "avgCost": 0,
    "duration": "2-3小时",
    "openTime": "08:00-18:00",
    "rating": 4.5
  },
  {
    "name": "黔灵山公园",
    "city": "贵阳",
    "category": "attraction",
    "description": "黔灵山公园是贵阳市区著名的综合性公园，集自然风光、文物古迹和民俗风情于一体，园内山清水秀，猕猴成群，是游客休闲观光的理想去处。",
    "tags": [
      "风景名胜",
      "国家级景点"
    ],
    "avgCost": 5,
    "duration": "2-3小时",
    "openTime": "08:00-18:00",
    "rating": 4.5
  },
  {
    "name": "贵厨酸汤牛肉(小十字店)",
    "city": "贵阳",
    "category": "food",
    "description": "贵厨酸汤牛肉(小十字店)是一家位于贵阳市南明区的中餐厅，以酸汤牛肉为特色，提供地道的贵州美食。",
    "tags": [
      "餐饮服务",
      "中餐厅"
    ],
    "avgCost": 0,
    "duration": "",
    "openTime": "",
    "rating": 3.5
  },
  {
    "name": "贵厨酸汤牛肉(汇金星力城店)",
    "city": "贵阳",
    "category": "food",
    "description": "贵厨酸汤牛肉位于汇金星力城六楼，是一家以贵州酸汤牛肉为特色的中餐厅。酸汤采用传统发酵工艺，汤底酸爽开胃，配以鲜嫩牛肉，口感丰富。环境整洁，服务热情，适合朋友聚餐或家庭用餐。",
    "tags": [
      "酸汤牛肉",
      "贵州菜",
      "火锅",
      "中餐厅"
    ],
    "avgCost": 70,
    "duration": "1.5小时",
    "openTime": "11:00-21:00",
    "rating": 4.5,
    "address": "新建路1号汇金星力城F6层",
    "region": "云岩区"
  },
  {
    "name": "贵厨酸汤牛肉(甲秀楼店)",
    "city": "贵阳",
    "category": "food",
    "description": "贵厨酸汤牛肉(甲秀楼店)是位于贵阳市南明区甲秀楼附近的一家酸汤牛肉餐厅，提供地道的贵州酸汤牛肉等美食。",
    "tags": [
      "酸汤牛肉",
      "贵州菜",
      "中餐厅"
    ],
    "avgCost": 80,
    "duration": "1-2小时",
    "openTime": "10:00-22:00",
    "rating": 4.5
  },
  {
    "name": "贵厨酸汤牛肉(花果园旗舰店)",
    "city": "贵阳",
    "category": "food",
    "description": "贵厨酸汤牛肉(花果园旗舰店)是一家位于贵阳市南明区花果园的中餐厅，主打贵州特色酸汤牛肉，口味酸辣开胃，深受当地食客喜爱。",
    "tags": [
      "酸汤牛肉",
      "贵州菜",
      "火锅",
      "中餐"
    ],
    "avgCost": 80,
    "duration": "2小时",
    "openTime": "10:00-22:00",
    "rating": 4.5
  },
  {
    "name": "贵厨酸汤牛肉(CCPARK店)",
    "city": "贵阳",
    "category": "food",
    "description": "贵厨酸汤牛肉(CCPARK店)位于观山湖区林城东路155号贵阳城投CCPARKB馆，是一家以酸汤牛肉为特色的云贵菜餐厅。酸汤牛肉是贵州经典菜肴，汤底酸辣开胃，牛肉鲜嫩，深受食客喜爱。店内环境舒适，服务周到，是品尝地道贵州风味的好去处。",
    "tags": [
      "云贵菜",
      "酸汤牛肉",
      "贵阳美食",
      "火锅"
    ],
    "avgCost": 60,
    "duration": "1.5小时",
    "openTime": "11:00-21:00",
    "rating": 4.5
  },
  {
    "name": "江边渔村(小十字总店)",
    "city": "贵阳",
    "category": "food",
    "description": "一家位于云岩区中山东路的海鲜酒楼，提供中餐服务。",
    "tags": [
      "海鲜",
      "中餐",
      "酒楼"
    ],
    "avgCost": 0,
    "duration": "",
    "openTime": "",
    "rating": 3.5
  },
  {
    "name": "贵厨酸汤牛肉(美的悦然广场店)",
    "city": "贵阳",
    "category": "food",
    "description": "贵厨酸汤牛肉是一家以酸汤牛肉为特色的火锅店，位于美的悦然广场三楼，提供地道贵州酸汤火锅体验。",
    "tags": [
      "酸汤牛肉",
      "火锅",
      "贵阳美食"
    ],
    "avgCost": 0,
    "duration": "未知",
    "openTime": "未知",
    "rating": 0
  },
  {
    "name": "黔渔翁豆花渎鱼(喷水池店)",
    "city": "贵阳",
    "category": "food",
    "description": "黔渔翁豆花渎鱼(喷水池店)是一家位于贵阳市云岩区的中餐厅，主打豆花渎鱼。",
    "tags": [
      "中餐厅"
    ],
    "avgCost": 0,
    "duration": "",
    "openTime": "",
    "rating": 3.5
  },
  {
    "name": "贵厨酸汤牛肉(世纪金源店)",
    "city": "贵阳",
    "category": "food",
    "description": "贵厨酸汤牛肉是贵阳特色酸汤牛肉火锅店，位于世纪金源购物中心C区4层，主打正宗黔味酸汤牛肉，汤底酸辣开胃，牛肉鲜嫩。",
    "tags": [
      "酸汤牛肉",
      "贵州菜",
      "火锅",
      "中餐厅"
    ],
    "avgCost": 80,
    "duration": "1.5小时",
    "openTime": "10:00-21:00",
    "rating": 4.5
  },
  {
    "name": "贵州西江传说苗侗餐饮活态博物馆",
    "city": "贵阳",
    "category": "food",
    "description": "贵州西江传说苗侗餐饮活态博物馆 是贵阳的美食餐厅，位于花溪区。地址：小河小孟工业园区同为物流园2栋。",
    "tags": [
      "贵阳"
    ],
    "avgCost": 0,
    "duration": "",
    "openTime": "全天",
    "rating": 3.5
  },
  {
    "name": "贵阳墅国际青年旅舍",
    "city": "贵阳",
    "category": "hotel",
    "description": "贵阳墅国际青年旅舍位于中山南路86号，云岩区，提供经济实惠的住宿服务。青年旅舍氛围轻松，适合背包客和旅行者。",
    "tags": [
      "青年旅舍",
      "住宿",
      "贵阳"
    ],
    "avgCost": 100,
    "duration": "全天",
    "openTime": "24小时",
    "rating": 4.0
  },
  {
    "name": "贵阳云贵招待所",
    "city": "贵阳",
    "category": "hotel",
    "description": "贵阳云贵招待所位于南明区沙冲北路，是一家提供住宿服务的旅馆招待所。",
    "tags": [
      "住宿服务",
      "旅馆招待所"
    ],
    "avgCost": 0,
    "duration": "",
    "openTime": "00:00-24:00",
    "rating": 0.0
  },
  {
    "name": "贵阳兴源酒店",
    "city": "贵阳",
    "category": "hotel",
    "description": "贵阳兴源酒店位于贵阳市乌当区新添寨新创路1号，提供舒适的住宿服务。",
    "tags": [
      "酒店",
      "住宿",
      "乌当区"
    ],
    "avgCost": 200,
    "duration": "1天",
    "openTime": "全天",
    "rating": 4.2
  },
  {
    "name": "小康旅社",
    "city": "贵阳",
    "category": "hotel",
    "description": "小康旅社位于贵州省贵阳市息烽县永靖镇下阳朗村虎城大道中段26号，提供住宿服务。",
    "tags": [
      "住宿",
      "旅馆招待所"
    ],
    "avgCost": 0,
    "duration": "未知",
    "openTime": "未知",
    "rating": 0
  },
  {
    "name": "锦程尚佳酒店(贵阳花果园财富广场店)",
    "city": "贵阳",
    "category": "hotel",
    "description": "锦程尚佳酒店(贵阳花果园财富广场店)位于贵阳市南明区花果园财富广场，是一家经济型连锁酒店，提供舒适的住宿服务。",
    "tags": [
      "经济型酒店",
      "连锁酒店",
      "花果园"
    ],
    "avgCost": 200,
    "duration": "全天",
    "openTime": "24小时",
    "rating": 4.2
  }
]